toasted/__init__.py
toasted/common.py
toasted/elements.py
toasted/enums.py
toasted/filesystem.py
toasted/history.py
toasted/toast.py
toasted-0.2.0.dist-info/LICENSE
toasted-0.2.0.dist-info/METADATA
toasted-0.2.0.dist-info/WHEEL
toasted-0.2.0.dist-info/top_level.txt
toasted-0.2.0.dist-info/RECORD
