Metadata-Version: 2.1
Name: toasted
Version: 0.2.0
Summary: Toast notifications library for Windows, built on top of WinRT.
Author: ysfchn
License: MIT License
Project-URL: GitHub, https://github.com/ysfchn/toasted
Project-URL: Sponsor, https://github.com/sponsors/ysfchn
Classifier: Programming Language :: Python :: 3.9
Classifier: License :: OSI Approved :: MIT License
Classifier: Operating System :: Microsoft :: Windows
Requires-Python: >=3.9
License-File: LICENSE
Requires-Dist: httpx ~=0.25.0
Requires-Dist: Pillow ~=10.2.0
Requires-Dist: winsdk ~=1.0.0b6 ; platform_system == "Windows"
